LICENSE
MANIFEST.in
README.md
setup.py
slokc/__init__.py
slokc.egg-info/PKG-INFO
slokc.egg-info/SOURCES.txt
slokc.egg-info/dependency_links.txt
slokc.egg-info/entry_points.txt
slokc.egg-info/not-zip-safe
slokc.egg-info/requires.txt
slokc.egg-info/top_level.txt
slokc/static/cock.svg
slokc/static/suck_lord_kelvin_cock.desktop