Metadata-Version: 1.0
Name: slokc
Version: 2021.12.8.2204
Summary: Kelvin Building automated Wi-Fi login program
Home-page: https://github.com/wdbm/suck_lord_kelvin_cock
Author: Will Breaden Madden
Author-email: wbm@protonmail.ch
License: GPLv3
Platform: UNKNOWN
